ze/__init__.py
ze/src/__init__.py
ze/src/core.py
ze/src/factory.py
ze/src/main.py
ze/src/manager.py
ze/src/models.py
ze/src/settings.py
zeconfig-0.1.4.dist-info/METADATA
zeconfig-0.1.4.dist-info/WHEEL
zeconfig-0.1.4.dist-info/top_level.txt
zeconfig-0.1.4.dist-info/RECORD
