Metadata-Version: 2.2
Name: zeconfig
Version: 0.1.4
Summary: Configuration Manager Package
Requires-Python: >=3.12
Requires-Dist: python-dotenv==1.0.1
Requires-Dist: pyyaml==6.0.2
Requires-Dist: tomli>=2.2.1
